mkpdfs_mkdocs/__init__.py
mkpdfs_mkdocs/generator.py
mkpdfs_mkdocs/mkpdfs.py
mkpdfs_mkdocs/utils.py
mkpdfs_mkdocs/design/FiraSans-Bold.otf
mkpdfs_mkdocs/design/FiraSans-Italic.otf
mkpdfs_mkdocs/design/FiraSans-Light.otf
mkpdfs_mkdocs/design/FiraSans-LightItalic.otf
mkpdfs_mkdocs/design/FiraSans-Regular.otf
mkpdfs_mkdocs/design/cover.jpg
mkpdfs_mkdocs/design/fonts/font-awesome.css
mkpdfs_mkdocs/design/fonts/material-icons.css
mkpdfs_mkdocs/design/fonts/specimen/FontAwesome.ttf
mkpdfs_mkdocs/design/fonts/specimen/FontAwesome.woff
mkpdfs_mkdocs/design/fonts/specimen/FontAwesome.woff2
mkpdfs_mkdocs/design/fonts/specimen/MaterialIcons-Regular.ttf
mkpdfs_mkdocs/design/fonts/specimen/MaterialIcons-Regular.woff
mkpdfs_mkdocs/design/fonts/specimen/MaterialIcons-Regular.woff2
mkpdfs_mkdocs/preprocessor/__init__.py
mkpdfs_mkdocs/preprocessor/prep.py
mkpdfs_mkdocs/preprocessor/links/__init__.py
mkpdfs_mkdocs/preprocessor/links/transform.py
mkpdfs_mkdocs/preprocessor/links/util.py
mkpdfs2_mkdocs-1.1.1.dist-info/LICENSE
mkpdfs2_mkdocs-1.1.1.dist-info/METADATA
mkpdfs2_mkdocs-1.1.1.dist-info/WHEEL
mkpdfs2_mkdocs-1.1.1.dist-info/entry_points.txt
mkpdfs2_mkdocs-1.1.1.dist-info/top_level.txt
mkpdfs2_mkdocs-1.1.1.dist-info/RECORD
