Metadata-Version: 2.1
Name: mkpdfs2-mkdocs
Version: 1.1.1
Summary: Allows the generation of the PDF version of your MkDocs documentation.
Home-page: https://github.com/jurgenwigg/mkpdfs2-mkdocs-plugin
Author: Comwes
Author-email: contact@comwes.eu
Maintainer: jurgenwigg
Maintainer-email: jurgenwigg@protonmail.com
License: GPLv3
Project-URL: Bug Reports, https://github.com/jurgenwigg/mkpdfs2-mkdocs-plugin/issues
Project-URL: Source, https://github.com/jurgenwigg/mkpdfs2-mkdocs-plugin
Keywords: mkdocs documentation pdf export weasyprint markdown plugin
Classifier: Development Status :: 4 - Beta
Classifier: Intended Audience :: Developers
Classifier: Intended Audience :: Education
Classifier: Intended Audience :: Information Technology
Classifier: Intended Audience :: System Administrators
Classifier: License :: OSI Approved :: GNU General Public License v3 (GPLv3)
Classifier: Topic :: Documentation
Classifier: Topic :: Printing
Classifier: Programming Language :: Other
Classifier: Programming Language :: Python :: 3 :: Only
Classifier: Programming Language :: Python :: 3.4
Classifier: Programming Language :: Python :: 3.5
Classifier: Programming Language :: Python :: 3.6
Classifier: Programming Language :: Python :: 3.7
Classifier: Programming Language :: Python :: 3.8
Requires-Python: >=3.4
License-File: LICENSE
Requires-Dist: mkdocs >=0.17
Requires-Dist: weasyprint >=0.44
Requires-Dist: beautifulsoup4 >=4.6.3
